mediapipe_apiserver/__init__.py
mediapipe_apiserver/__main__.py
mediapipe_apiserver/camera/__init__.py
mediapipe_apiserver/camera/camera_interface.py
mediapipe_apiserver/camera/kinect_camera.py
mediapipe_apiserver/common/__init__.py
mediapipe_apiserver/common/option.py
mediapipe_apiserver/common/utils.py
mediapipe_apiserver/detector/__init__.py
mediapipe_apiserver/detector/mediapipe.py
mediapipe_apiserver/restful/__init__.py
mediapipe_apiserver/restful/controller.py
mediapipe_apiserver/restful/detector.py
mediapipe_apiserver-0.1.0.dist-info/METADATA
mediapipe_apiserver-0.1.0.dist-info/WHEEL
mediapipe_apiserver-0.1.0.dist-info/top_level.txt
mediapipe_apiserver-0.1.0.dist-info/RECORD
